tablemage/__init__.py
tablemage/_base/__init__.py
tablemage/_reports/__init__.py
tablemage/_src/__init__.py
tablemage/_src/analyzer.py
tablemage/_src/causal/__init__.py
tablemage/_src/causal/causal_model.py
tablemage/_src/causal/report.py
tablemage/_src/causal/causalutils/__init__.py
tablemage/_src/causal/causalutils/methods.py
tablemage/_src/causal/causalutils/models.py
tablemage/_src/data/__init__.py
tablemage/_src/data/dataemitter.py
tablemage/_src/data/datahandler.py
tablemage/_src/data/preprocessing.py
tablemage/_src/data/utils/__init__.py
tablemage/_src/data/utils/formula.py
tablemage/_src/data/utils/var_naming.py
tablemage/_src/display/__init__.py
tablemage/_src/display/plot_options.py
tablemage/_src/display/print_options.py
tablemage/_src/display/print_utils.py
tablemage/_src/exploratory/__init__.py
tablemage/_src/exploratory/eda.py
tablemage/_src/feature_selection/__init__.py
tablemage/_src/feature_selection/base_feature_selection.py
tablemage/_src/feature_selection/boruta_feature_selection.py
tablemage/_src/feature_selection/classification_feature_selection.py
tablemage/_src/feature_selection/regression_feature_selection.py
tablemage/_src/feature_selection/voteselect_report.py
tablemage/_src/feature_selection/BorutaPy/__init__.py
tablemage/_src/feature_selection/BorutaPy/boruta_py.py
tablemage/_src/linear/__init__.py
tablemage/_src/linear/lm_rlike_util.py
tablemage/_src/linear/logit.py
tablemage/_src/linear/mnlogit.py
tablemage/_src/linear/ols.py
tablemage/_src/linear/lmutils/__init__.py
tablemage/_src/linear/lmutils/constants.py
tablemage/_src/linear/lmutils/funcs.py
tablemage/_src/linear/lmutils/plot.py
tablemage/_src/linear/lmutils/score.py
tablemage/_src/linear/reports/__init__.py
tablemage/_src/linear/reports/linearreport_utils.py
tablemage/_src/linear/reports/logit_report.py
tablemage/_src/linear/reports/mnlogit_report.py
tablemage/_src/linear/reports/ols_report.py
tablemage/_src/metrics/__init__.py
tablemage/_src/metrics/classification_scoring.py
tablemage-0.1.0a1.dist-info/METADATA
tablemage-0.1.0a1.dist-info/WHEEL
tablemage-0.1.0a1.dist-info/licenses/LICENSE
tablemage-0.1.0a1.dist-info/RECORD
