Metadata-Version: 2.4
Name: tablemage
Version: 0.1.0a1
Summary: A Python package for low-code analysis of tabular data
Project-URL: Homepage, https://tablemage.readthedocs.io/
Author-email: Andrew Yang <andrew_j_yang@brown.edu>, Joshua Woo <joshua_woo@brown.edu>, Ryan Zhang <rzryanz00@gmail.com>
License: Copyright 2025 Andrew Yang
License-File: LICENSE
Keywords: data science,low-code,machine learning,no-code,statistics
Classifier: Programming Language :: Python
Requires-Python: <3.13,>=3.10
Requires-Dist: adjusttext==1.2.0
Requires-Dist: matplotlib==3.9.2
Requires-Dist: numpy==1.26.4
Requires-Dist: optuna-integration==4.0.0
Requires-Dist: optuna==4.0.0
Requires-Dist: pandas==2.2.2
Requires-Dist: scikit-learn==1.5.2
Requires-Dist: scipy==1.14.1
Requires-Dist: seaborn==0.13.2
Requires-Dist: statsmodels==0.14.3
Requires-Dist: tableone==0.9.1
Requires-Dist: umap-learn==0.5.7
Requires-Dist: xgboost==2.1.1
Provides-Extra: agents
Requires-Dist: fastembed==0.5.0; extra == 'agents'
Requires-Dist: flask-cors==5.0.0; extra == 'agents'
Requires-Dist: flask==3.0.3; extra == 'agents'
Requires-Dist: llama-index-embeddings-fastembed==0.3.0; extra == 'agents'
Requires-Dist: llama-index-llms-groq==0.3.1; extra == 'agents'
Requires-Dist: llama-index-llms-ollama==0.5.0; extra == 'agents'
Requires-Dist: llama-index-llms-openai==0.3.12; extra == 'agents'
Requires-Dist: llama-index==0.12.13; extra == 'agents'
Requires-Dist: python-dotenv==1.0.1; extra == 'agents'
